{"track_3fRCAPMMZ8l8P9YKI6OCzD":{"timestamp":1784395333463,"data":{"type":"track","title":"drop dead","artist":"Olivia Rodrigo","allArtists":"Olivia Rodrigo","album":"you seem pretty sad for a girl so in love","year":"2026","trackNumber":1,"totalTracks":13,"coverUrl":"https://i.scdn.co/image/ab67616d0000b2736949b83f85d782b21ce70583","spotifyId":"3fRCAPMMZ8l8P9YKI6OCzD","spotifyUrl":"https://open.spotify.com/track/3fRCAPMMZ8l8P9YKI6OCzD","durationMs":224998,"artistThumbnail":"https://i.scdn.co/image/ab6761610000e5ebb14eb4dcfd2f3858bed06e44"}},"track_0yO9QD2Ga7eUzqnNYsSSPo":{"timestamp":1784395514048,"data":{"type":"track","title":"drop dead","artist":"Olivia Rodrigo","allArtists":"Olivia Rodrigo","album":"you seem pretty sad for a girl so in love","year":"2026","trackNumber":1,"totalTracks":13,"coverUrl":"https://i.scdn.co/image/ab67616d0000b2735cf234eeb7a2edf44bf64a46","spotifyId":"0yO9QD2Ga7eUzqnNYsSSPo","spotifyUrl":"https://open.spotify.com/track/0yO9QD2Ga7eUzqnNYsSSPo","durationMs":224998,"artistThumbnail":"https://i.scdn.co/image/ab6761610000e5ebb14eb4dcfd2f3858bed06e44"}},"track_47EiUVwUp4C9fGccaPuUCS":{"timestamp":1784395578032,"data":{"type":"track","title":"DÁKITI","artist":"Bad Bunny","allArtists":"Bad Bunny, JHAYCO","album":"DÁKITI","year":"2020","trackNumber":1,"totalTracks":1,"coverUrl":"https://i.scdn.co/image/ab67616d0000b27334c8199b0b3b3fb42b8a98a8","spotifyId":"47EiUVwUp4C9fGccaPuUCS","spotifyUrl":"https://open.spotify.com/track/47EiUVwUp4C9fGccaPuUCS","durationMs":205090,"artistThumbnail":"https://i.scdn.co/image/ab6761610000e5eb81f47f44084e0a09b5f0fa13"}},"track_6b9OaVk0TxWsHMH0OjWLMO":{"timestamp":1784397646614,"data":{"type":"track","title":"Sexy For Me","artist":"Jason Derulo","allArtists":"Jason Derulo","album":"The Last Dance (Part 1)","year":"2026","trackNumber":1,"totalTracks":8,"coverUrl":"https://i.scdn.co/image/ab67616d0000b273aa798b71b0468714bd0db131","spotifyId":"6b9OaVk0TxWsHMH0OjWLMO","spotifyUrl":"https://open.spotify.com/track/6b9OaVk0TxWsHMH0OjWLMO","durationMs":128155,"artistThumbnail":"https://i.scdn.co/image/ab6761610000e5ebfb65e1af01cf95c25bd29ed1"}},"track_6zKrj4SomgfbvsfuTAuElE":{"timestamp":1784403331525,"data":{"type":"track","title":"Want to Want Me","artist":"Jason Derulo","allArtists":"Jason Derulo","album":"Everything Is 4","year":"2015","trackNumber":1,"totalTracks":11,"coverUrl":"https://i.scdn.co/image/ab67616d0000b273c8ef608c30067dd8d3a80f56","spotifyId":"6zKrj4SomgfbvsfuTAuElE","spotifyUrl":"https://open.spotify.com/track/6zKrj4SomgfbvsfuTAuElE","durationMs":207719,"artistThumbnail":"https://i.scdn.co/image/ab6761610000e5ebfb65e1af01cf95c25bd29ed1"}},"album_6s84u2TUpR3wdUv4NgKA2j":{"timestamp":1784472638755,"data":{"type":"album","title":"SOUR","artist":"Olivia Rodrigo","allArtists":"Olivia Rodrigo","year":"2021","coverUrl":"https://i.scdn.co/image/ab67616d0000b273a91c10fe9472d9bd89802e5a","artistThumbnail":"https://i.scdn.co/image/ab6761610000e5ebb14eb4dcfd2f3858bed06e44","trackCount":11,"totalTracks":11,"spotifyId":"6s84u2TUpR3wdUv4NgKA2j","tracks":[{"trackNumber":1,"title":"brutal","artist":"Olivia Rodrigo","allArtists":"Olivia Rodrigo","album":"SOUR","year":"2021","coverUrl":"https://i.scdn.co/image/ab67616d0000b273a91c10fe9472d9bd89802e5a","spotifyId":"6SRsiMl7w1USE4mFqrOhHC","spotifyUrl":"https://open.spotify.com/track/6SRsiMl7w1USE4mFqrOhHC","durationMs":143746,"totalTracks":11},{"trackNumber":2,"title":"traitor","artist":"Olivia Rodrigo","allArtists":"Olivia Rodrigo","album":"SOUR","year":"2021","coverUrl":"https://i.scdn.co/image/ab67616d0000b273a91c10fe9472d9bd89802e5a","spotifyId":"5CZ40GBx1sQ9agT82CLQCT","spotifyUrl":"https://open.spotify.com/track/5CZ40GBx1sQ9agT82CLQCT","durationMs":229226,"totalTracks":11},{"trackNumber":3,"title":"drivers license","artist":"Olivia Rodrigo","allArtists":"Olivia Rodrigo","album":"SOUR","year":"2021","coverUrl":"https://i.scdn.co/image/ab67616d0000b273a91c10fe9472d9bd89802e5a","spotifyId":"5wANPM4fQCJwkGd4rN57mH","spotifyUrl":"https://open.spotify.com/track/5wANPM4fQCJwkGd4rN57mH","durationMs":242013,"totalTracks":11},{"trackNumber":4,"title":"1 step forward, 3 steps back","artist":"Olivia Rodrigo","allArtists":"Olivia Rodrigo","album":"SOUR","year":"2021","coverUrl":"https://i.scdn.co/image/ab67616d0000b273a91c10fe9472d9bd89802e5a","spotifyId":"4wcBRRpIfesgcyUtis7PEg","spotifyUrl":"https://open.spotify.com/track/4wcBRRpIfesgcyUtis7PEg","durationMs":163586,"totalTracks":11},{"trackNumber":5,"title":"deja vu","artist":"Olivia Rodrigo","allArtists":"Olivia Rodrigo","album":"SOUR","year":"2021","coverUrl":"https://i.scdn.co/image/ab67616d0000b273a91c10fe9472d9bd89802e5a","spotifyId":"6HU7h9RYOaPRFeh0R3UeAr","spotifyUrl":"https://open.spotify.com/track/6HU7h9RYOaPRFeh0R3UeAr","durationMs":215506,"totalTracks":11},{"trackNumber":6,"title":"good 4 u","artist":"Olivia Rodrigo","allArtists":"Olivia Rodrigo","album":"SOUR","year":"2021","coverUrl":"https://i.scdn.co/image/ab67616d0000b273a91c10fe9472d9bd89802e5a","spotifyId":"4ZtFanR9U6ndgddUvNcjcG","spotifyUrl":"https://open.spotify.com/track/4ZtFanR9U6ndgddUvNcjcG","durationMs":178146,"totalTracks":11},{"trackNumber":7,"title":"enough for you","artist":"Olivia Rodrigo","allArtists":"Olivia Rodrigo","album":"SOUR","year":"2021","coverUrl":"https://i.scdn.co/image/ab67616d0000b273a91c10fe9472d9bd89802e5a","spotifyId":"2TOzTqQXNmR2zDJXihjZ2e","spotifyUrl":"https://open.spotify.com/track/2TOzTqQXNmR2zDJXihjZ2e","durationMs":202826,"totalTracks":11},{"trackNumber":8,"title":"happier","artist":"Olivia Rodrigo","allArtists":"Olivia Rodrigo","album":"SOUR","year":"2021","coverUrl":"https://i.scdn.co/image/ab67616d0000b273a91c10fe9472d9bd89802e5a","spotifyId":"2tGvwE8GcFKwNdAXMnlbfl","spotifyUrl":"https://open.spotify.com/track/2tGvwE8GcFKwNdAXMnlbfl","durationMs":175933,"totalTracks":11},{"trackNumber":9,"title":"jealousy, jealousy","artist":"Olivia Rodrigo","allArtists":"Olivia Rodrigo","album":"SOUR","year":"2021","coverUrl":"https://i.scdn.co/image/ab67616d0000b273a91c10fe9472d9bd89802e5a","spotifyId":"0MMyJUC3WNnFS1lit5pTjk","spotifyUrl":"https://open.spotify.com/track/0MMyJUC3WNnFS1lit5pTjk","durationMs":173160,"totalTracks":11},{"trackNumber":10,"title":"favorite crime","artist":"Olivia Rodrigo","allArtists":"Olivia Rodrigo","album":"SOUR","year":"2021","coverUrl":"https://i.scdn.co/image/ab67616d0000b273a91c10fe9472d9bd89802e5a","spotifyId":"5JCoSi02qi3jJeHdZXMmR8","spotifyUrl":"https://open.spotify.com/track/5JCoSi02qi3jJeHdZXMmR8","durationMs":152666,"totalTracks":11},{"trackNumber":11,"title":"hope ur ok","artist":"Olivia Rodrigo","allArtists":"Olivia Rodrigo","album":"SOUR","year":"2021","coverUrl":"https://i.scdn.co/image/ab67616d0000b273a91c10fe9472d9bd89802e5a","spotifyId":"1zejeOnykpCoyVSit6Bwp3","spotifyUrl":"https://open.spotify.com/track/1zejeOnykpCoyVSit6Bwp3","durationMs":209560,"totalTracks":11}]}}}